pylaundry/__init__.py
pylaundry/const.py
pylaundry/exceptions.py
pylaundry/helpers.py
tests/__init__.py
tests/conftest.py
tests/test_basics.py
tests/http_bodies/__init__.py
pylaundry-0.1.5.dist-info/LICENSE
pylaundry-0.1.5.dist-info/METADATA
pylaundry-0.1.5.dist-info/WHEEL
pylaundry-0.1.5.dist-info/top_level.txt
pylaundry-0.1.5.dist-info/zip-safe
pylaundry-0.1.5.dist-info/RECORD
