Metadata-Version: 2.1
Name: pylaundry
Version: 0.1.5
Summary: Python library for viewing laundry room and account status for facilities using ESD payment equipment.
Home-page: https://github.com/elahd/pylaundry
Author: Elahd Bar-Shai
Author-email: pylaundry@elahd.com
License: MIT
Project-URL: Bug Tracker, https://github.com/elahd/pylaundry/issues
Classifier: Programming Language :: Python :: 3
Classifier: License :: OSI Approved :: MIT License
Classifier: Operating System :: OS Independent
Requires-Python: >=3.9
License-File: LICENSE
Requires-Dist: aiohttp (>=3.8.1)
Requires-Dist: cryptography (>=36.0.2)
